AUTHORS
LICENSE
MANIFEST.in
README
setup.py
pyrandint/__init__.py
pyrandint.egg-info/PKG-INFO
pyrandint.egg-info/SOURCES.txt
pyrandint.egg-info/dependency_links.txt
pyrandint.egg-info/not-zip-safe
pyrandint.egg-info/top_level.txt