Metadata-Version: 1.0
Name: pyrandint
Version: 0.1
Summary: A python library for randint.com's api.
Home-page: UNKNOWN
Author: UNKNOWN
Author-email: UNKNOWN
License: BSD
Platform: any
Classifier: Development Status :: 2 - Pre-Alpha
Classifier: Intended Audience :: Developers
Classifier: License :: OSI Approved :: BSD License
Classifier: Operating System :: OS Independent
Classifier: Programming Language :: Python
Classifier: Topic :: Software Development :: Libraries :: Python Modules
